common/__init__.py
common/constants.py
common/entities.py
common/exceptions.py
common/utils.py
convert/__init__.py
convert/convert_key.py
convert/convert_type.py
convert/convert_value.py
convert/register.py
core/__init__.py
core/assigner.py
core/converter.py
core/picker.py
core/transformer.py
jsonpath2path-0.1.0.dist-info/LICENSE
jsonpath2path-0.1.0.dist-info/METADATA
jsonpath2path-0.1.0.dist-info/WHEEL
jsonpath2path-0.1.0.dist-info/top_level.txt
jsonpath2path-0.1.0.dist-info/RECORD
