Metadata-Version: 2.1
Name: jsonpath2path
Version: 0.1.0
Summary: jsonpath2path - JSON Data Transformation Tool.
Home-page: https://github.com/dengquanxin/jsonpath2path
Author: DENGQUANXIN
Author-email: 2507120731@qq.com
License: Apache-2.0
Classifier: Programming Language :: Python :: 3
Classifier: License :: OSI Approved :: Apache Software License
Classifier: Operating System :: OS Independent
Requires-Python: >=3.9
License-File: LICENSE
Requires-Dist: jsonpath-ng >=1.7.0
Requires-Dist: lark >=1.2.2
